README.rst
setup.py
./LICENSE
./__init__.py
./interpreterlist.py
./tox_globinterpreter.py
tox_globinterpreter.egg-info/PKG-INFO
tox_globinterpreter.egg-info/SOURCES.txt
tox_globinterpreter.egg-info/dependency_links.txt
tox_globinterpreter.egg-info/namespace_packages.txt
tox_globinterpreter.egg-info/requires.txt
tox_globinterpreter.egg-info/top_level.txt